tests/__init__.py
tkbrowser-0.0.1.dist-info/LICENSE
tkbrowser-0.0.1.dist-info/METADATA
tkbrowser-0.0.1.dist-info/WHEEL
tkbrowser-0.0.1.dist-info/entry_points.txt
tkbrowser-0.0.1.dist-info/top_level.txt
tkbrowser-0.0.1.dist-info/RECORD
