Metadata-Version: 2.1
Name: tkbrowser
Version: 0.0.1
Summary: secret
Home-page: https://github.com/pyrustic/tkbrowser
Author: Pyrustic Evangelist
Author-email: pyrustic@protonmail.com
Maintainer: Pyrustic Evangelist
Maintainer-email: pyrustic@protonmail.com
License: MIT
Keywords: gui,pattern,widgets,frontend,tkinter
Platform: UNKNOWN
Classifier: Programming Language :: Python :: 3
Classifier: License :: OSI Approved :: MIT License
Classifier: Operating System :: OS Independent
Requires-Python: >=3.5
